codeinterpreter/__init__.py
codeinterpreter/adapter/__init__.py
codeinterpreter/adapter/openai.py
codeinterpreter/sandbox/__init__.py
codeinterpreter/sandbox/docker_jupyter/__init__.py
codeinterpreter/sandbox/kubernetes_jupyter/__init__.py
codeinterpreter/sandbox/local_jupyter/__init__.py
codeinterpreter/sandbox/local_jupyter/manager.py
codeinterpreter/sandbox/local_jupyter/sandbox.py
codeinterpreter/sandbox/manager.py
codeinterpreter/sandbox/sandbox.py
codeinterpreter/sandbox/schema.py
codeinterpreter/utils/__init__.py
codeinterpreter/utils/dependency.py
codeinterpreter/utils/error.py
codeinterpreter/utils/log.py
codeinterpreter-0.0.1.dist-info/LICENSE
codeinterpreter-0.0.1.dist-info/METADATA
codeinterpreter-0.0.1.dist-info/WHEEL
codeinterpreter-0.0.1.dist-info/RECORD
