Metadata-Version: 2.1
Name: codeinterpreter
Version: 0.0.1
Summary: The Best Open Source LLM Code Interpreter.
License: Apache-2.0
Author: arcosx
Author-email: arcosx@outlook.com
Requires-Python: >=3.8,<4.0
Classifier: License :: OSI Approved :: Apache Software License
Classifier: Programming Language :: Python :: 3
Classifier: Programming Language :: Python :: 3.8
Classifier: Programming Language :: Python :: 3.9
Classifier: Programming Language :: Python :: 3.10
Classifier: Programming Language :: Python :: 3.11
Requires-Dist: aiohttp (==3.8.5)
Requires-Dist: jupyter-kernel-gateway (==2.5.2)
Requires-Dist: pydantic (==2.1.1)
Requires-Dist: requests (==2.31.0)
Requires-Dist: websockets (==11.0.3)
